{
  "times": [
    "5:21 AM",
    "3:18 PM",
    "9:23 PM",
    "9:35 PM",
    "10:32 PM",
    "8:02 AM",
    "11:51 AM"
  ],
  "voteIncrements": {
    "KISH": [
      0,
      0,
      0,
      0,
      0,
      0,
      0
    ],
    "DUSTBIA": [
      0,
      1,
      1,
      0,
      0,
      0,
      0
    ],
    "BREKA": [
      0,
      0,
      0,
      0,
      0,
      0,
      0
    ],
    "WILLCA": [
      11,
      0,
      0,
      6,
      98,
      1,
      1
    ],
    "AZRALPH": [
      0,
      0,
      0,
      0,
      0,
      0,
      0
    ]
  },
  "baselineVotes": {
    "KISH": 102472,
    "DUSTBIA": 35097159,
    "BREKA": 127179,
    "WILLCA": 1036436358,
    "AZRALPH": 179356
  },
  "updateTimesPH": [
    "08/12/2025, 06:10:26",
    "08/12/2025, 16:14:53",
    "08/12/2025, 21:27:40",
    "08/12/2025, 22:11:24",
    "08/12/2025, 23:11:25",
    "08/13/2025, 08:53:14",
    "08/13/2025, 12:21:34"
  ]
}