{
  "times": [
    "2:06 AM",
    "3:06 AM",
    "4:09 AM",
    "5:09 AM",
    "6:00 AM",
    "7:10 AM",
    "8:59 AM"
  ],
  "voteIncrements": {
    "KISH": [
      788,
      16,
      4,
      0,
      0,
      0,
      2
    ],
    "DUSTBIA": [
      133054,
      50317,
      6319,
      393,
      275,
      637,
      1085
    ],
    "BREKA": [
      84,
      76,
      3,
      0,
      0,
      35,
      0
    ],
    "WILLCA": [
      1000273293,
      72046,
      7949,
      123,
      697,
      474,
      2475
    ],
    "AZRALPH": [
      114,
      99,
      88,
      0,
      0,
      0,
      0
    ]
  },
  "baselineVotes": {
    "KISH": 102472,
    "DUSTBIA": 35095606,
    "BREKA": 127179,
    "WILLCA": 1036434277,
    "AZRALPH": 179355
  },
  "updateTimesPH": [
    "08/10/2025, 02:14:12",
    "08/10/2025, 03:07:49",
    "08/10/2025, 04:10:53",
    "08/10/2025, 05:09:01",
    "08/10/2025, 06:10:01",
    "08/10/2025, 07:10:27",
    "08/10/2025, 08:59:59"
  ]
}